ColorfulCLI/__init__.py
ColorfulCLI/colorful.py
ColorfulCLI-0.0.1.dist-info/LICENSE
ColorfulCLI-0.0.1.dist-info/METADATA
ColorfulCLI-0.0.1.dist-info/WHEEL
ColorfulCLI-0.0.1.dist-info/top_level.txt
ColorfulCLI-0.0.1.dist-info/RECORD
