Metadata-Version: 2.1
Name: ColorfulCLI
Version: 0.0.1
Summary: A simple, effective way to add color to your CLI apps.
Author: Dave Bowlin
Author-email: davebowlin@gmail.com
Classifier: Programming Language :: Python :: 3
Classifier: License :: OSI Approved :: MIT License
Classifier: Operating System :: OS Independent
Requires-Python: >=3.6
License-File: LICENSE
